setup.py
flapsk/__init__.py
flapsk/foo.py
flapsk.egg-info/PKG-INFO
flapsk.egg-info/SOURCES.txt
flapsk.egg-info/dependency_links.txt
flapsk.egg-info/not-zip-safe
flapsk.egg-info/top_level.txt