Metadata-Version: 1.0
Name: flapsk
Version: 0.3.1
Summary: The funniest joke in the world
Home-page: UNKNOWN
Author: UNKNOWN
Author-email: UNKNOWN
License: MIT
Platform: UNKNOWN
